nestedaccess/__init__.py
nestedaccess/lang.py
nestedaccess/nestedaccess.py
nestedaccess-1.1.3.dist-info/LICENSE
nestedaccess-1.1.3.dist-info/METADATA
nestedaccess-1.1.3.dist-info/WHEEL
nestedaccess-1.1.3.dist-info/top_level.txt
nestedaccess-1.1.3.dist-info/RECORD
