Metadata-Version: 2.1
Name: nestedaccess
Version: 1.1.3
Summary: Nestedaccess is a simple, elegant way to retrieve nested data from deep dictionaries or lists.
Home-page: https://github.com/Potato-OvO/nestedaccess
Author: Potato-OvO
Author-email: wkl1224141267@gmail.com
License: MIT
Platform: UNKNOWN
Classifier: License :: OSI Approved :: MIT License
Classifier: Development Status :: 5 - Production/Stable
Classifier: Topic :: Utilities
Classifier: Operating System :: OS Independent
Classifier: Programming Language :: Python :: 3
Classifier: Programming Language :: Python :: 3.7
Classifier: Programming Language :: Python :: 3.8
Classifier: Programming Language :: Python :: 3.9
Classifier: Programming Language :: Python :: 3.10
Classifier: Programming Language :: Python :: Implementation :: CPython
Classifier: Programming Language :: Python :: Implementation :: PyPy
Requires-Python: >=3.7.0
